{
  "sizes": [
    5,
    3,
    1
  ],
  "layers": [
    {
      "shoulderlength": {},
      "waistcircumference": {},
      "Age": {},
      "Heightin": {},
      "Weightlbs\r": {}
    },
    {
      "0": {
        "bias": 0.2722872197628021,
        "weights": {
          "shoulderlength": -0.03890198469161987,
          "waistcircumference": 0.5320265293121338,
          "Age": -0.07715675234794617,
          "Heightin": 0.151876762509346,
          "Weightlbs\r": 0.23297496140003204
        }
      },
      "1": {
        "bias": 0.06613746285438538,
        "weights": {
          "shoulderlength": 0.12065890431404114,
          "waistcircumference": 0.25976255536079407,
          "Age": 0.16245943307876587,
          "Heightin": 0.0921177938580513,
          "Weightlbs\r": -0.14334870874881744
        }
      },
      "2": {
        "bias": 0.35069984197616577,
        "weights": {
          "shoulderlength": 0.004994026850908995,
          "waistcircumference": 0.37521499395370483,
          "Age": 0.00480748200789094,
          "Heightin": 0.04744478687644005,
          "Weightlbs\r": -0.006927901413291693
        }
      }
    },
    {
      "Gender": {
        "bias": -1.7894001007080078,
        "weights": {
          "0": -1.3966225385665894,
          "1": -1.1104402542114258,
          "2": -1.3097325563430786
        }
      }
    }
  ],
  "outputLookup": true,
  "inputLookup": true,
  "activation": "sigmoid",
  "trainOpts": {
    "iterations": 20000,
    "errorThresh": 0.005,
    "log": false,
    "logPeriod": 10,
    "learningRate": 0.3,
    "momentum": 0.1,
    "callbackPeriod": 10
  }
}